{"id": 1, "document_theme": 1, "currency_id": null, "organization_id": 2, "payment_details": "Account Name       Multi-Pay Solutions Ltd\r\nAccount Number    026419000000019\r\nIBAN                       MU62AFBL2501026419000000019USD\r\nBeneficiary Bank     AfrAsia Bank Ltd\r\nSWIFT Code            AFBLMUMU\r\nCountry                   Mauritius", "application_version": "0.0.1", "use_backups": true, "backup_frequency": "D", "verification_task_id": "d612e7a4fff2dbefe3779b1d2131d8023ffb8ab6", "is_configured": true, "logo_aspect_ratio": 3}